package_outlier/__init__.py
package_outlier-0.9.dist-info/LICENSE
package_outlier-0.9.dist-info/METADATA
package_outlier-0.9.dist-info/WHEEL
package_outlier-0.9.dist-info/entry_points.txt
package_outlier-0.9.dist-info/top_level.txt
package_outlier-0.9.dist-info/RECORD
