Metadata-Version: 2.1
Name: package-outlier
Version: 0.9
Summary: This is an outlier detection package
Home-page: https://github.com/jainyk/package-outlier
License: MIT
Platform: UNKNOWN
Classifier: License :: OSI Approved :: MIT License
Classifier: Programming Language :: Python :: 3
Classifier: Programming Language :: Python :: 3.7
Requires-Dist: scipy
Requires-Dist: numpy
Requires-Dist: pandas
Requires-Dist: scikit-learn
Requires-Dist: statistics
Requires-Dist: datetime
